typedllm/__init__.py
typedllm/client.py
typedllm/interop.py
typedllm/models.py
typedllm/prompt.py
typedllm/tool.py
typedllm/version.py
typedllm-0.3.3.dist-info/METADATA
typedllm-0.3.3.dist-info/WHEEL
typedllm-0.3.3.dist-info/licenses/LICENSE
typedllm-0.3.3.dist-info/RECORD
