Metadata-Version: 2.3
Name: typedllm
Version: 0.3.3
Summary: A Pydantic LLM Interface that sparks Joy
Author-email: Todd Cullen <todd@100-x.ai>
License: MIT
License-File: LICENSE
Requires-Python: >=3.9
Requires-Dist: httpx>=0.27.0
Requires-Dist: litellm>=1.34.25
Requires-Dist: pydantic>=2.1.0
Requires-Dist: typedtemplate>=0.2.1
